reporails_cli/.env.example
reporails_cli/__init__.py
reporails_cli/py.typed
reporails_cli/bundled/.semgrepignore
reporails_cli/bundled/__init__.py
reporails_cli/bundled/capability-patterns.yml
reporails_cli/bundled/levels.yml
reporails_cli/core/__init__.py
reporails_cli/core/agents.py
reporails_cli/core/applicability.py
reporails_cli/core/bootstrap.py
reporails_cli/core/cache.py
reporails_cli/core/capability.py
reporails_cli/core/discover.py
reporails_cli/core/engine.py
reporails_cli/core/init.py
reporails_cli/core/levels.py
reporails_cli/core/models.py
reporails_cli/core/registry.py
reporails_cli/core/sarif.py
reporails_cli/core/scorer.py
reporails_cli/core/semantic.py
reporails_cli/core/utils.py
reporails_cli/core/opengrep/__init__.py
reporails_cli/core/opengrep/runner.py
reporails_cli/core/opengrep/semgrepignore.py
reporails_cli/core/opengrep/templates.py
reporails_cli/formatters/__init__.py
reporails_cli/formatters/json.py
reporails_cli/formatters/mcp.py
reporails_cli/formatters/text/__init__.py
reporails_cli/formatters/text/box.py
reporails_cli/formatters/text/chars.py
reporails_cli/formatters/text/compact.py
reporails_cli/formatters/text/components.py
reporails_cli/formatters/text/full.py
reporails_cli/formatters/text/rules.py
reporails_cli/formatters/text/violations.py
reporails_cli/interfaces/__init__.py
reporails_cli/interfaces/cli/__init__.py
reporails_cli/interfaces/cli/main.py
reporails_cli/interfaces/mcp/__init__.py
reporails_cli/interfaces/mcp/server.py
reporails_cli/interfaces/mcp/tools.py
reporails_cli/templates/__init__.py
reporails_cli/templates/cli_box.txt
reporails_cli/templates/cli_cta.txt
reporails_cli/templates/cli_delta.txt
reporails_cli/templates/cli_file_header.txt
reporails_cli/templates/cli_legend.txt
reporails_cli/templates/cli_pending.txt
reporails_cli/templates/cli_violation.txt
reporails_cli/templates/cli_working.txt
reporails_cli-0.0.2.dist-info/METADATA
reporails_cli-0.0.2.dist-info/WHEEL
reporails_cli-0.0.2.dist-info/entry_points.txt
reporails_cli-0.0.2.dist-info/licenses/LICENSE
reporails_cli-0.0.2.dist-info/RECORD
