Metadata-Version: 2.4
Name: reporails-cli
Version: 0.0.2
Summary: Lint and score CLAUDE.md files — MCP-first AI context governance
Project-URL: Homepage, https://github.com/reporails/cli
Project-URL: Documentation, https://reporails.dev/docs
Project-URL: Repository, https://github.com/reporails/cli
Project-URL: Issues, https://github.com/reporails/cli/issues
Author: Reporails Team
License: Apache-2.0
License-File: LICENSE
Keywords: ai,claude,claude-code,context,lint,mcp
Classifier: Development Status :: 3 - Alpha
Classifier: Environment :: Console
Classifier: Intended Audience :: Developers
Classifier: License :: OSI Approved :: Apache Software License
Classifier: Programming Language :: Python :: 3.11
Classifier: Programming Language :: Python :: 3.12
Classifier: Topic :: Software Development :: Quality Assurance
Requires-Python: >=3.11
Requires-Dist: httpx>=0.27.0
Requires-Dist: mcp>=1.0.0
Requires-Dist: pydantic>=2.0.0
Requires-Dist: pyyaml>=6.0.0
Requires-Dist: rich>=13.0.0
Requires-Dist: typer>=0.12.0
Provides-Extra: dev
Requires-Dist: mypy>=1.8.0; extra == 'dev'
Requires-Dist: poethepoet>=0.25.0; extra == 'dev'
Requires-Dist: pytest-cov>=4.0.0; extra == 'dev'
Requires-Dist: pytest>=8.0.0; extra == 'dev'
Requires-Dist: ruff>=0.3.0; extra == 'dev'
Requires-Dist: types-pyyaml>=6.0.0; extra == 'dev'
